nycschools/__init__.py
nycschools/budgets.py
nycschools/cep.py
nycschools/class_size.py
nycschools/dataloader.py
nycschools/datasets.py
nycschools/exams.py
nycschools/geo.py
nycschools/nysed.py
nycschools/schools.py
nycschools/segregation.py
nycschools/shsat.py
nycschools/snapshot.py
nycschools/tools.py
nycschools/ui.py
nycschools-0.1.18.1.dist-info/licenses/LICENSE
nycschools-0.1.18.1.dist-info/METADATA
nycschools-0.1.18.1.dist-info/WHEEL
nycschools-0.1.18.1.dist-info/top_level.txt
nycschools-0.1.18.1.dist-info/RECORD
