Metadata-Version: 2.4
Name: nycschools
Version: 0.1.18.1
Summary: Tools to work with open data about New York City public schools
Author-email: "Matthew X. Curinga" <matt@curinga.com>
Project-URL: Homepage, https://adelphi-ed-tech.github.io/nycschools/
Project-URL: Bug Tracker, https://github.com/adelphi-ed-tech/nycschools/issues
Project-URL: Source, https://github.com/adelphi-ed-tech/nycschools
Keywords: opendata, schools, newyorkcity, maps
Classifier: Development Status :: 3 - Alpha
Classifier: License :: OSI Approved :: GNU Affero General Public License v3 or later (AGPLv3+)
Classifier: Operating System :: OS Independent
Classifier: Programming Language :: Python :: 3
Classifier: Programming Language :: Python :: 3.8
Classifier: Programming Language :: Python :: 3.9
Classifier: Programming Language :: Python :: 3.10
Classifier: Intended Audience :: Developers
Classifier: Intended Audience :: Education
Classifier: Intended Audience :: Science/Research
Classifier: Natural Language :: English
Classifier: Framework :: Jupyter
Classifier: Topic :: Education
Requires-Python: >=3.8
License-File: LICENSE
Requires-Dist: arrow
Requires-Dist: beautifulsoup4
Requires-Dist: build
Requires-Dist: invoke
Requires-Dist: folium
Requires-Dist: geopandas
Requires-Dist: geopy
Requires-Dist: html5lib
Requires-Dist: humanize
Requires-Dist: ipython
Requires-Dist: lxml
Requires-Dist: mapclassify
Requires-Dist: matplotlib
Requires-Dist: networkx
Requires-Dist: nbformat
Requires-Dist: numpy
Requires-Dist: openpyxl
Requires-Dist: pandas
Requires-Dist: plotly
Requires-Dist: pingouin
Requires-Dist: py7zr
Requires-Dist: pyarrow
Requires-Dist: python-dotenv
Requires-Dist: python-Levenshtein
Requires-Dist: pyodbc
Requires-Dist: pytest
Requires-Dist: requests
Requires-Dist: scikit-learn
Requires-Dist: seaborn
Requires-Dist: selenium
Requires-Dist: thefuzz
Requires-Dist: toml
Requires-Dist: twine
Requires-Dist: wget
Requires-Dist: xyzservices
Requires-Dist: yaspin
Dynamic: license-file
